fluentpy/__init__.py
fluentpy/__main__.py
fluentpy/wrapper.py
fluentpy-2.1.1.dist-info/LICENSE
fluentpy-2.1.1.dist-info/METADATA
fluentpy-2.1.1.dist-info/WHEEL
fluentpy-2.1.1.dist-info/top_level.txt
fluentpy-2.1.1.dist-info/RECORD
