Metadata-Version: 2.1
Name: fluentpy
Version: 2.1.1
Summary: Python wrapper for stdlib (and your) objects to give them a fluent interface.
Home-page: https://github.com/dwt/fluent
Author: Martin Häcker
Author-email: mhaecker@mac.com
License: ISC
Project-URL: Documentation, https://fluentpy.readthedocs.io/
Keywords: wrapper,smalltalk,ruby,fluent,interface,functional
Platform: UNKNOWN
Classifier: Development Status :: 5 - Production/Stable
Classifier: Environment :: Console
Classifier: Intended Audience :: Developers
Classifier: Topic :: Software Development :: Libraries
Classifier: Topic :: Utilities
Classifier: License :: OSI Approved :: ISC License (ISCL)
Classifier: Programming Language :: Python :: 3
Requires-Python: >=3.6
Provides-Extra: dev
Requires-Dist: twine ; extra == 'dev'
Provides-Extra: docs
Requires-Dist: sphinx (>=1.8.3) ; extra == 'docs'
Requires-Dist: sphinx-rtd-theme (>=0.4.2) ; extra == 'docs'
Requires-Dist: autoapi (>=1.3.1) ; extra == 'docs'
Requires-Dist: recommonmark (>=0.5.0) ; extra == 'docs'
Provides-Extra: tests
Requires-Dist: pyexpect ; extra == 'tests'
Requires-Dist: pytest ; extra == 'tests'
Requires-Dist: tox ; extra == 'tests'
